async_bioservices/__init__.py
async_bioservices/db2db.py
async_bioservices/input_database.py
async_bioservices/output_database.py
async_bioservices/taxon_id.py
async_bioservices-2.1.0.dist-info/METADATA
async_bioservices-2.1.0.dist-info/WHEEL
async_bioservices-2.1.0.dist-info/RECORD
