Metadata-Version: 2.1
Name: async-bioservices
Version: 2.1.0
Summary: This is an asynchronous method of accessing bioservice's db2db function
Author: Josh Loecker
Author-email: joshloecker@icloud.com
Requires-Python: >=3.9,<3.12
Classifier: Programming Language :: Python :: 3
Classifier: Programming Language :: Python :: 3.9
Classifier: Programming Language :: Python :: 3.10
Classifier: Programming Language :: Python :: 3.11
Requires-Dist: aiosqlite (>=0.19.0)
Requires-Dist: bioservices (<2)
Requires-Dist: pandas (>=1.4.4)
